codeallyadvanced/__init__.py
codeallyadvanced/_version.py
codeallyadvanced/py.typed
codeallyadvanced/resources/__init__.py
codeallyadvanced/resources/py.typed
codeallyadvanced/resources/images/DefaultPreferences.py
codeallyadvanced/resources/images/__init__.py
codeallyadvanced/resources/images/folder.py
codeallyadvanced/resources/images/py.typed
codeallyadvanced/resources/images/icons/__init__.py
codeallyadvanced/resources/images/icons/embedded16/ImgToolboxActor.py
codeallyadvanced/resources/images/icons/embedded16/ImgToolboxArrow.py
codeallyadvanced/resources/images/icons/embedded16/ImgToolboxClass.py
codeallyadvanced/resources/images/icons/embedded16/ImgToolboxNewClassDiagram.py
codeallyadvanced/resources/images/icons/embedded16/ImgToolboxNewProject.py
codeallyadvanced/resources/images/icons/embedded16/ImgToolboxNewSequenceDiagram.py
codeallyadvanced/resources/images/icons/embedded16/ImgToolboxNewUseCaseDiagram.py
codeallyadvanced/resources/images/icons/embedded16/ImgToolboxNote.py
codeallyadvanced/resources/images/icons/embedded16/ImgToolboxOpenFile.py
codeallyadvanced/resources/images/icons/embedded16/ImgToolboxRedo.py
codeallyadvanced/resources/images/icons/embedded16/ImgToolboxRelationshipAggregation.py
codeallyadvanced/resources/images/icons/embedded16/ImgToolboxRelationshipAssociation.py
codeallyadvanced/resources/images/icons/embedded16/ImgToolboxRelationshipComposition.py
codeallyadvanced/resources/images/icons/embedded16/ImgToolboxRelationshipInheritance.py
codeallyadvanced/resources/images/icons/embedded16/ImgToolboxRelationshipNote.py
codeallyadvanced/resources/images/icons/embedded16/ImgToolboxRelationshipRealization.py
codeallyadvanced/resources/images/icons/embedded16/ImgToolboxSaveDiagram.py
codeallyadvanced/resources/images/icons/embedded16/ImgToolboxSequenceDiagramInstance.py
codeallyadvanced/resources/images/icons/embedded16/ImgToolboxSequenceDiagramMessage.py
codeallyadvanced/resources/images/icons/embedded16/ImgToolboxText.py
codeallyadvanced-2.3.0.dist-info/licenses/LICENSE
codeallyadvanced-2.3.0.dist-info/METADATA
codeallyadvanced-2.3.0.dist-info/WHEEL
codeallyadvanced-2.3.0.dist-info/top_level.txt
codeallyadvanced-2.3.0.dist-info/RECORD
