Metadata-Version: 2.4
Name: codeallyadvanced
Version: 2.3.0
Summary: Humberto`s Common wxPython UI Stuff
Author-email: "Humberto A. Sanchez II" <Humberto.A.Sanchez.II@gmail.com>
Maintainer-email: "Humberto A. Sanchez II" <Humberto.A.Sanchez.II@gmail.com>
License-Expression: AGPL-1.0-or-later
Project-URL: Repository, https://github.com/hasii2011/code-ally-advanced
Keywords: pyut,python,wxPython,UI,umldiagrammer
Classifier: Programming Language :: Python
Classifier: Intended Audience :: Developers
Classifier: Operating System :: MacOS :: MacOS X
Classifier: Topic :: Software Development :: Libraries :: Python Modules
License-File: LICENSE
Requires-Dist: buildlackey>=2.0.0
Requires-Dist: wxPython>=4.2.4
Provides-Extra: test
Requires-Dist: mypy==1.18.2; extra == "test"
Requires-Dist: codeallybasic==1.30.0; extra == "test"
Requires-Dist: mypy-extensions==1.1.0; extra == "test"
Requires-Dist: types-Deprecated==1.3.1.20251101; extra == "test"
Requires-Dist: html-testRunner~=1.2.1; extra == "test"
Provides-Extra: deploy
Requires-Dist: wheel==0.45.1; extra == "deploy"
Requires-Dist: setuptools==80.9.0; extra == "deploy"
Requires-Dist: twine==6.2.0; extra == "deploy"
Requires-Dist: build==1.3.0; extra == "deploy"
Dynamic: license-file
